cmem_plugin_base/__init__.py
cmem_plugin_base/dataintegration/__init__.py
cmem_plugin_base/dataintegration/context.py
cmem_plugin_base/dataintegration/description.py
cmem_plugin_base/dataintegration/discovery.py
cmem_plugin_base/dataintegration/entity.py
cmem_plugin_base/dataintegration/parameter/__init__.py
cmem_plugin_base/dataintegration/parameter/choice.py
cmem_plugin_base/dataintegration/parameter/code.py
cmem_plugin_base/dataintegration/parameter/dataset.py
cmem_plugin_base/dataintegration/parameter/graph.py
cmem_plugin_base/dataintegration/parameter/multiline.py
cmem_plugin_base/dataintegration/parameter/password.py
cmem_plugin_base/dataintegration/parameter/resource.py
cmem_plugin_base/dataintegration/plugins.py
cmem_plugin_base/dataintegration/ports.py
cmem_plugin_base/dataintegration/typed_entities/__init__.py
cmem_plugin_base/dataintegration/typed_entities/file.py
cmem_plugin_base/dataintegration/typed_entities/quads.py
cmem_plugin_base/dataintegration/typed_entities/typed_entities.py
cmem_plugin_base/dataintegration/types.py
cmem_plugin_base/dataintegration/utils/__init__.py
cmem_plugin_base/dataintegration/utils/entity_builder.py
cmem_plugin_base/testing.py
cmem_plugin_base-4.15.0.dist-info/METADATA
cmem_plugin_base-4.15.0.dist-info/WHEEL
cmem_plugin_base-4.15.0.dist-info/licenses/LICENSE
cmem_plugin_base-4.15.0.dist-info/RECORD
