Metadata-Version: 2.4
Name: cmem-plugin-base
Version: 4.15.0
Summary: Base classes for developing eccenca Corporate Memory plugins.
License: Apache-2.0
License-File: LICENSE
Keywords: eccenca Corporate Memory,plugins,DataIntegration
Author: eccenca GmbH
Author-email: cmempy-developer@eccenca.com
Maintainer: Sebastian Tramp
Maintainer-email: sebastian.tramp@eccenca.com
Requires-Python: >=3.13,<4.0
Classifier: Development Status :: 5 - Production/Stable
Classifier: Environment :: Plugins
Classifier: License :: OSI Approved :: Apache Software License
Classifier: Programming Language :: Python :: 3
Classifier: Programming Language :: Python :: 3.13
Classifier: Programming Language :: Python :: 3.14
Classifier: Topic :: Software Development :: Libraries :: Python Modules
Requires-Dist: cmem-cmempy (>=25.2.0)
Requires-Dist: pydantic (>=2.12.2,<3.0.0)
Requires-Dist: python-ulid (>=3.1.0,<4.0.0)
Project-URL: Homepage, https://github.com/eccenca/cmem-plugin-base
